airtablemock/__init__.py
airtablemock/__init__.pyi
airtablemock/py.typed
airtablemock-0.0.11.dist-info/AUTHORS
airtablemock-0.0.11.dist-info/METADATA
airtablemock-0.0.11.dist-info/WHEEL
airtablemock-0.0.11.dist-info/pbr.json
airtablemock-0.0.11.dist-info/top_level.txt
airtablemock-0.0.11.dist-info/RECORD
