Metadata-Version: 2.1
Name: airtablemock
Version: 0.0.11
Summary: Mock library for the airtable python client
Home-page: https://github.com/bayesimpact/airtablemock
Author: Pascal Corpet
Author-email: UNKNOWN
License: The MIT License (MIT)
Keywords: airtable,api,mock
Platform: UNKNOWN
Classifier: Development Status :: 3 - Alpha
Classifier: Intended Audience :: Developers
Classifier: Operating System :: MacOS :: MacOS X
Classifier: Operating System :: Microsoft :: Windows
Classifier: Operating System :: POSIX
Classifier: Programming Language :: Python :: 3
Classifier: Programming Language :: Python :: 3.3
Classifier: Programming Language :: Python :: 3.4
Classifier: Programming Language :: Python :: 3.5
Classifier: Programming Language :: Python :: 3.6
Classifier: Programming Language :: Python :: 3.7
Classifier: Programming Language :: Python :: 3.8
Classifier: Programming Language :: Python :: 3.9
Classifier: Programming Language :: Python :: Implementation :: CPython
Classifier: Programming Language :: Python :: Implementation :: PyPy
Classifier: Topic :: Software Development :: Libraries :: Python Modules
Requires-Dist: mock (>=2.0.0)
Requires-Dist: parsimonious (>=0.8.1)
Requires-Dist: requests
